joblib/__init__.py
joblib/_dask.py
joblib/_deprecated_format_stack.py
joblib/_deprecated_my_exceptions.py
joblib/_memmapping_reducer.py
joblib/_multiprocessing_helpers.py
joblib/_parallel_backends.py
joblib/_store_backends.py
joblib/backports.py
joblib/compressor.py
joblib/disk.py
joblib/executor.py
joblib/format_stack.py
joblib/func_inspect.py
joblib/hashing.py
joblib/logger.py
joblib/memory.py
joblib/my_exceptions.py
joblib/numpy_pickle.py
joblib/numpy_pickle_compat.py
joblib/numpy_pickle_utils.py
joblib/parallel.py
joblib/pool.py
joblib/testing.py
joblib/externals/__init__.py
joblib/externals/cloudpickle/__init__.py
joblib/externals/cloudpickle/cloudpickle.py
joblib/externals/cloudpickle/cloudpickle_fast.py
joblib/externals/cloudpickle/compat.py
joblib/externals/loky/__init__.py
joblib/externals/loky/_base.py
joblib/externals/loky/cloudpickle_wrapper.py
joblib/externals/loky/process_executor.py
joblib/externals/loky/reusable_executor.py
joblib/externals/loky/backend/__init__.py
joblib/externals/loky/backend/_posix_reduction.py
joblib/externals/loky/backend/_posix_wait.py
joblib/externals/loky/backend/_win_reduction.py
joblib/externals/loky/backend/_win_wait.py
joblib/externals/loky/backend/compat.py
joblib/externals/loky/backend/compat_posix.py
joblib/externals/loky/backend/compat_win32.py
joblib/externals/loky/backend/context.py
joblib/externals/loky/backend/fork_exec.py
joblib/externals/loky/backend/managers.py
joblib/externals/loky/backend/popen_loky_posix.py
joblib/externals/loky/backend/popen_loky_win32.py
joblib/externals/loky/backend/process.py
joblib/externals/loky/backend/queues.py
joblib/externals/loky/backend/reduction.py
joblib/externals/loky/backend/resource_tracker.py
joblib/externals/loky/backend/semlock.py
joblib/externals/loky/backend/spawn.py
joblib/externals/loky/backend/synchronize.py
joblib/externals/loky/backend/utils.py
joblib/test/__init__.py
joblib/test/common.py
joblib/test/test_backports.py
joblib/test/test_dask.py
joblib-1.0.0.dist-info/LICENSE.txt
joblib-1.0.0.dist-info/METADATA
joblib-1.0.0.dist-info/WHEEL
joblib-1.0.0.dist-info/top_level.txt
joblib-1.0.0.dist-info/RECORD
